contribcast/__init__.py
contribcast/cli.py
contribcast/forecast.py
contribcast/github_agent.py
contribcast/github_auto_pr.py
contribcast/github_llm_agent.py
contribcast/local_llm_agent.py
contribcast/notifier.py
contribcast/scheduler.py
contribcast-0.1.1.dist-info/METADATA
contribcast-0.1.1.dist-info/WHEEL
contribcast-0.1.1.dist-info/entry_points.txt
contribcast-0.1.1.dist-info/top_level.txt
contribcast-0.1.1.dist-info/RECORD
