Metadata-Version: 2.4
Name: contribcast
Version: 0.1.1
Summary: AI-powered GitHub contribution forecasting and automation agent
Author-email: Adesoji Alu <adesoji.alu@gmail.com>
License: MIT
Project-URL: Homepage, https://github.com/adesoji1/contribcast
Project-URL: Repository, https://github.com/adesoji1/contribcast
Project-URL: Documentation, https://github.com/adesoji1/contribcast#readme
Keywords: github,contributions,cli,ai,openai,productivity
Classifier: Programming Language :: Python :: 3
Classifier: License :: OSI Approved :: MIT License
Classifier: Operating System :: OS Independent
Classifier: Development Status :: 3 - Alpha
Classifier: Intended Audience :: Developers
Classifier: Environment :: Console
Classifier: Topic :: Software Development :: Version Control :: Git
Requires-Python: >=3.11
Requires-Dist: requests
Requires-Dist: click
Requires-Dist: langchain
Requires-Dist: langchain-openai
Requires-Dist: openai
Requires-Dist: python-dotenv
Requires-Dist: seaborn
Requires-Dist: matplotlib
Requires-Dist: schedule
Requires-Dist: slack_sdk
Requires-Dist: twilio
